ppf/sample/__init__.py
ppf/sample/cli.py
ppf/sample/module.py
ppf/sample/package_data.dat
ppf/sample/utils.py
ppf.sample-3.0.0.data/data/my_data/data_file
ppf.sample-3.0.0.dist-info/LICENSE
ppf.sample-3.0.0.dist-info/METADATA
ppf.sample-3.0.0.dist-info/WHEEL
ppf.sample-3.0.0.dist-info/entry_points.txt
ppf.sample-3.0.0.dist-info/top_level.txt
ppf.sample-3.0.0.dist-info/RECORD
